{"cameraMode":{"drawMode":0,"name":"Shaded","section":"Shading Mode"},"sceneLighting":false,"audioPlay":false,"sceneViewState":{"m_AlwaysRefresh":false,"showFog":true,"showSkybox":false,"showFlares":true,"showImageEffects":true,"showParticleSystems":true,"showVisualEffectGraphs":true,"m_FxEnabled":true},"in2DMode":false,"pivot":{"x":9.604104042053223,"y":-2.5950984954833986,"z":11.480268478393555},"rotation":{"x":-0.09347856044769287,"y":-0.32331541180610659,"z":0.03210771828889847,"w":-0.9411254525184631},"size":10.0,"orthographic":false}